code/Color_Moments_GLCM.py
code/__init__.py
code/evaluate_model_performance.py
code/model_train.py
unpaved_road_condition_analysis/Autokeras_model.py
unpaved_road_condition_analysis/Color_Moments_GLCM.py
unpaved_road_condition_analysis/Color_Moments_GLCM_Complex.py
unpaved_road_condition_analysis/Color_Moments_GLCM_IMG.py
unpaved_road_condition_analysis/__init__.py
unpaved_road_condition_analysis/calculate_color_histogram.py
unpaved_road_condition_analysis/calculate_contour_properties.py
unpaved_road_condition_analysis/calculate_fourier_transform.py
unpaved_road_condition_analysis/calculate_hog_features.py
unpaved_road_condition_analysis/calculate_lbp_features.py
unpaved_road_condition_analysis/evaluate_model_performance.py
unpaved_road_condition_analysis/load_image.py
unpaved_road_condition_analysis/model_train.py
unpaved_road_condition_analysis/multimodal_prediction.py
unpaved_road_condition_analysis/process_img_to_PCA.py
unpaved_road_condition_analysis/process_road_condition_data.py
unpaved_road_condition_analysis/standardize_images.py
unpaved_road_condition_analysis-0.0.1.dist-info/LICENSE
unpaved_road_condition_analysis-0.0.1.dist-info/METADATA
unpaved_road_condition_analysis-0.0.1.dist-info/WHEEL
unpaved_road_condition_analysis-0.0.1.dist-info/top_level.txt
unpaved_road_condition_analysis-0.0.1.dist-info/RECORD
